<?xml version="1.0" encoding="UTF-8"?>
<!--prefab resource-->
<WorldObj name="RootNode">
    <Transform>
        <Translation x="0" y="0" z="0"/>
        <Rotation x="0" y="0" z="0"/>
        <Scale x="1" y="1" z="1"/>
    </Transform>
    <WorldObj name="Root">
        <Transform>
            <Translation x="0" y="0" z="0"/>
            <Rotation x="0" y="0" z="0"/>
            <Scale x="1" y="1" z="1"/>
        </Transform>
        <WorldObj name="Bone1">
            <Transform>
                <Translation x="0" y="0" z="0"/>
                <Rotation x="0" y="0" z="0"/>
                <Scale x="1" y="1" z="1"/>
            </Transform>
        </WorldObj>
        <WorldObj name="Bone2">
            <Transform>
                <Translation x="0" y="0" z="0"/>
                <Rotation x="0" y="0" z="0"/>
                <Scale x="1" y="1" z="1"/>
            </Transform>
        </WorldObj>
        <WorldObj name="Bone3">
            <Transform>
                <Translation x="2.0231097" y="45.265713" z="-2.2325506"/>
                <Rotation x="0" y="0" z="0"/>
                <Scale x="1" y="1" z="1"/>
            </Transform>
        </WorldObj>
        <WorldObj name="Bone4">
            <Transform>
                <Translation x="2.0231097" y="45.265713" z="-2.2325506"/>
                <Rotation x="0" y="0" z="0"/>
                <Scale x="1" y="1" z="1"/>
            </Transform>
        </WorldObj>
        <WorldObj name="Bone5">
            <Transform>
                <Translation x="2.0231097" y="45.265713" z="-2.2325506"/>
                <Rotation x="0" y="0" z="0"/>
                <Scale x="1" y="1" z="1"/>
            </Transform>
        </WorldObj>
        <WorldObj name="Bone6">
            <Transform>
                <Translation x="2.0231097" y="45.265713" z="-2.2325506"/>
                <Rotation x="0" y="0" z="0"/>
                <Scale x="1" y="1" z="1"/>
            </Transform>
        </WorldObj>
        <WorldObj name="Bone7">
            <Transform>
                <Translation x="2.0231097" y="45.265713" z="-2.2325506"/>
                <Rotation x="0" y="0" z="0"/>
                <Scale x="1" y="1" z="1"/>
            </Transform>
        </WorldObj>
        <WorldObj name="Bone8">
            <Transform>
                <Translation x="2.0231097" y="45.265713" z="-2.2325506"/>
                <Rotation x="0" y="0" z="0"/>
                <Scale x="1" y="1" z="1"/>
            </Transform>
        </WorldObj>
        <WorldObj name="Bone9">
            <Transform>
                <Translation x="2.0231097" y="45.265713" z="-2.2325506"/>
                <Rotation x="0" y="0" z="0"/>
                <Scale x="1" y="1" z="1"/>
            </Transform>
        </WorldObj>
        <WorldObj name="Bone10">
            <Transform>
                <Translation x="2.0231097" y="45.265713" z="-2.2325506"/>
                <Rotation x="0" y="0" z="0"/>
                <Scale x="1" y="1" z="1"/>
            </Transform>
        </WorldObj>
        <WorldObj name="Bone11">
            <Transform>
                <Translation x="-15.41802" y="55.393005" z="10.263825"/>
                <Rotation x="0" y="0" z="0"/>
                <Scale x="1" y="1" z="1"/>
            </Transform>
        </WorldObj>
        <WorldObj name="Bone12">
            <Transform>
                <Translation x="-15.41802" y="55.393005" z="10.263825"/>
                <Rotation x="0" y="0" z="0"/>
                <Scale x="1" y="1" z="1"/>
            </Transform>
        </WorldObj>
        <WorldObj name="Bone13">
            <Transform>
                <Translation x="-15.41802" y="55.393005" z="10.263825"/>
                <Rotation x="0" y="0" z="0"/>
                <Scale x="1" y="1" z="1"/>
            </Transform>
        </WorldObj>
        <WorldObj name="Bone14">
            <Transform>
                <Translation x="-15.41802" y="55.393005" z="10.263825"/>
                <Rotation x="0" y="0" z="0"/>
                <Scale x="1" y="1" z="1"/>
            </Transform>
        </WorldObj>
        <WorldObj name="Bone15">
            <Transform>
                <Translation x="-15.41802" y="55.393005" z="10.263825"/>
                <Rotation x="0" y="0" z="0"/>
                <Scale x="1" y="1" z="1"/>
            </Transform>
        </WorldObj>
        <WorldObj name="Bone16">
            <Transform>
                <Translation x="-15.41802" y="55.393005" z="10.263825"/>
                <Rotation x="0" y="0" z="0"/>
                <Scale x="1" y="1" z="1"/>
            </Transform>
        </WorldObj>
        <WorldObj name="Bone17">
            <Transform>
                <Translation x="-15.41802" y="55.393005" z="10.263825"/>
                <Rotation x="0" y="0" z="0"/>
                <Scale x="1" y="1" z="1"/>
            </Transform>
        </WorldObj>
    </WorldObj>
    <WorldObj name="Env_Pottery">
        <Transform>
            <Translation x="0" y="0" z="0"/>
            <Rotation x="0" y="0" z="0"/>
            <Scale x="1" y="1" z="1"/>
        </Transform>
        <Mesh refPath="./data/mesh/Env_Pottery.mesh">
            <Material refPath="./data/material/Prop_Stuff_005_26_Mat.smat.xml"/>
        </Mesh>
    </WorldObj>
</WorldObj>
