<?xml version="1.0" encoding="UTF-8"?>
<!--prefab resource-->
<WorldObj name="RootNode">
    <Transform>
        <Translation x="0" y="0" z="0"/>
        <Rotation x="0" y="0" z="0"/>
        <Scale x="1" y="1" z="1"/>
    </Transform>
    <WorldObj name="Root">
        <Transform>
            <Translation x="0" y="0" z="0"/>
            <Rotation x="0" y="0" z="0"/>
            <Scale x="1" y="1" z="1"/>
        </Transform>
        <WorldObj name="Bone1">
            <Transform>
                <Translation x="0" y="0" z="0"/>
                <Rotation x="0" y="0" z="0"/>
                <Scale x="1" y="1" z="1"/>
            </Transform>
        </WorldObj>
        <WorldObj name="Bone2">
            <Transform>
                <Translation x="8.564723" y="14.20146" z="-6.2076555e-007"/>
                <Rotation x="0" y="0" z="0"/>
                <Scale x="1" y="1" z="1"/>
            </Transform>
        </WorldObj>
    </WorldObj>
    <WorldObj name="Env_StoneT">
        <Transform>
            <Translation x="0" y="0" z="0"/>
            <Rotation x="0" y="0" z="0"/>
            <Scale x="1" y="1" z="1"/>
        </Transform>
        <Mesh refPath="./data/mesh/Env_StoneT.mesh">
            <Material refPath="./data/material/Stone_001_Mat.smat.xml"/>
        </Mesh>
    </WorldObj>
</WorldObj>
